virtuered/__init__.py
virtuered/cli/__init__.py
virtuered/cli/commands.py
virtuered/client/__init__.py
virtuered/client/server.py
virtuered/webui/__init__.py
virtuered/webui/cli.py
virtuered/webui/server.py
virtuered/webui/frontend/404.html
virtuered/webui/frontend/config.js
virtuered/webui/frontend/dashboard.html
virtuered/webui/frontend/dashboard.txt
virtuered/webui/frontend/favicon.ico
virtuered/webui/frontend/file.svg
virtuered/webui/frontend/globe.svg
virtuered/webui/frontend/index.html
virtuered/webui/frontend/index.txt
virtuered/webui/frontend/models.html
virtuered/webui/frontend/models.txt
virtuered/webui/frontend/next.svg
virtuered/webui/frontend/progress.html
virtuered/webui/frontend/progress.txt
virtuered/webui/frontend/runs.html
virtuered/webui/frontend/runs.txt
virtuered/webui/frontend/vercel.svg
virtuered/webui/frontend/window.svg
virtuered/webui/frontend/_next/static/chunks/201-b9d33e18028354d7.js
virtuered/webui/frontend/_next/static/chunks/4bd1b696-9094e013355a9834.js
virtuered/webui/frontend/_next/static/chunks/508-216c62365afa40b3.js
virtuered/webui/frontend/_next/static/chunks/629.f0b62c69ed7322f7.js
virtuered/webui/frontend/_next/static/chunks/643-70fd7e44c0d42067.js
virtuered/webui/frontend/_next/static/chunks/684-946d9d1fa989fb11.js
virtuered/webui/frontend/_next/static/chunks/766-ea43befa0d36139b.js
virtuered/webui/frontend/_next/static/chunks/808-41087d2f2b9a0c99.js
virtuered/webui/frontend/_next/static/chunks/817-f84cf30f3da842df.js
virtuered/webui/frontend/_next/static/chunks/874-51f7136ed064388a.js
virtuered/webui/frontend/_next/static/chunks/8e1d74a4-652f6b40d1652731.js
virtuered/webui/frontend/_next/static/chunks/904-bf664209a367efdb.js
virtuered/webui/frontend/_next/static/chunks/966-f53b5ea58466e920.js
virtuered/webui/frontend/_next/static/chunks/9c4e2130-72e6352738e0319a.js
virtuered/webui/frontend/_next/static/chunks/ee560e2c-6e557a7c62a7b9a0.js
virtuered/webui/frontend/_next/static/chunks/f97e080b-a9c0a6632c441bf7.js
virtuered-2.1.1.dist-info/licenses/LICENSE
virtuered-2.1.1.dist-info/METADATA
virtuered-2.1.1.dist-info/WHEEL
virtuered-2.1.1.dist-info/entry_points.txt
virtuered-2.1.1.dist-info/top_level.txt
virtuered-2.1.1.dist-info/RECORD
