Metadata-Version: 2.4
Name: virtuered
Version: 2.1.1
Summary: CLI tool and Model Server for VirtueAI VirtueRed
Home-page: https://github.com/Virtue-AI/VirtueRed-CLI.git
Author: Virtue AI
Author-email: yijiazheng@virtueai.com
License: MIT
Classifier: Programming Language :: Python :: 3
Classifier: License :: OSI Approved :: MIT License
Classifier: Operating System :: OS Independent
Requires-Python: >=3.6
License-File: LICENSE
Requires-Dist: requests>=2.25.1
Requires-Dist: rich>=10.0.0
Requires-Dist: flask>=2.0.0
Requires-Dist: flask-cors>=3.0.0
Requires-Dist: waitress>=2.0.0
Requires-Dist: pyyaml>=6.0.0
Requires-Dist: fastapi>=0.70.0
Requires-Dist: uvicorn[standard]>=0.15.0
Requires-Dist: click>=7.0
Requires-Dist: pyfiglet>=0.8
Dynamic: author
Dynamic: author-email
Dynamic: classifier
Dynamic: description
Dynamic: description-content-type
Dynamic: home-page
Dynamic: license
Dynamic: license-file
Dynamic: requires-dist
Dynamic: requires-python
Dynamic: summary
